lazy_redis_log/__init__.py
lazy_redis_log/lazy_redis_log.py
lazy_redis_log-0.1.3.dist-info/METADATA
lazy_redis_log-0.1.3.dist-info/WHEEL
lazy_redis_log-0.1.3.dist-info/RECORD
