Metadata-Version: 2.1
Name: lazy-redis-log
Version: 0.1.3
Summary: Like print, but also writes to Redis Streams!
Author: MisterNyan
Author-email: michael.edmund.wong@gmail.com
Requires-Python: >=3.8,<4.0
Classifier: Programming Language :: Python :: 3
Classifier: Programming Language :: Python :: 3.8
Classifier: Programming Language :: Python :: 3.9
Classifier: Programming Language :: Python :: 3.10
Classifier: Programming Language :: Python :: 3.11
Classifier: Programming Language :: Python :: 3.12
Requires-Dist: redis (>=5.0.2,<6.0.0)
